README.rst
setup.cfg
setup.py
pybvc/__init__.py
pybvc.egg-info/PKG-INFO
pybvc.egg-info/SOURCES.txt
pybvc.egg-info/dependency_links.txt
pybvc.egg-info/not-zip-safe
pybvc.egg-info/requires.txt
pybvc.egg-info/top_level.txt
pybvc/common/__init__.py
pybvc/common/constants.py
pybvc/common/result.py
pybvc/common/status.py
pybvc/common/utils.py
pybvc/controller/__init__.py
pybvc/controller/controller.py
pybvc/controller/inventory.py
pybvc/controller/netconfnode.py
pybvc/controller/notification.py
pybvc/controller/openflownode.py
pybvc/controller/topology.py
pybvc/netconfdev/__init__.py
pybvc/netconfdev/vdx/__init__.py
pybvc/netconfdev/vdx/nos.py
pybvc/netconfdev/vrouter/__init__.py
pybvc/netconfdev/vrouter/firewall.py
pybvc/netconfdev/vrouter/interfaces.py
pybvc/netconfdev/vrouter/protocols.py
pybvc/netconfdev/vrouter/vpn.py
pybvc/netconfdev/vrouter/vrouter5600.py
pybvc/openflowdev/__init__.py
pybvc/openflowdev/ofswitch.py